aws_cdk/asset_kubectl_v22/__init__.py
aws_cdk/asset_kubectl_v22/py.typed
aws_cdk/asset_kubectl_v22/_jsii/__init__.py
aws_cdk/asset_kubectl_v22/_jsii/asset-kubectl-v22@0.0.3.jsii.tgz
aws_cdk.asset_kubectl_v22-0.0.3.dist-info/LICENSE
aws_cdk.asset_kubectl_v22-0.0.3.dist-info/METADATA
aws_cdk.asset_kubectl_v22-0.0.3.dist-info/NOTICE
aws_cdk.asset_kubectl_v22-0.0.3.dist-info/WHEEL
aws_cdk.asset_kubectl_v22-0.0.3.dist-info/top_level.txt
aws_cdk.asset_kubectl_v22-0.0.3.dist-info/RECORD
